MANIFEST.in
README.rst
setup.py
yac/__init__.py
yac.egg-info/PKG-INFO
yac.egg-info/SOURCES.txt
yac.egg-info/dependency_links.txt
yac.egg-info/not-zip-safe
yac.egg-info/requires.txt
yac.egg-info/top_level.txt
yac/bin/yac
yac/cli/__init__.py
yac/cli/__init__.pyc
yac/cli/build.py
yac/cli/build.pyc
yac/cli/clidriver.py
yac/cli/clidriver.pyc
yac/cli/container.py
yac/cli/container.pyc
yac/cli/params.py
yac/cli/params.pyc
yac/cli/prefs.py
yac/cli/prefs.pyc
yac/cli/primer.py
yac/cli/primer.pyc
yac/cli/push.py
yac/cli/push.pyc
yac/cli/registry.py
yac/cli/registry.pyc
yac/cli/restoredb.py
yac/cli/service.py
yac/cli/service.pyc
yac/cli/ssh.py
yac/cli/ssh.pyc
yac/cli/stack.py
yac/cli/stack.pyc
yac/cli/start.py
yac/cli/start.pyc
yac/cli/stop.py
yac/cli/task.py
yac/cli/task.pyc
yac/cli/test.pyc
yac/config/app/dbconn/bamboo.cfg.xml
yac/config/app/dbconn/confluence.cfg.xml
yac/config/app/dbconn/crowd.cfg.xml
yac/config/app/dbconn/dbconfig.xml
yac/config/stack/yac-asg-stack.json
yac/config/stack/yac-db-stack.json
yac/config/stack/yac-eelb-stack.json
yac/config/stack/yac-efs-stack.json
yac/config/stack/yac-ielb-stack.json
yac/lib/__init__.py
yac/lib/__init__.pyc
yac/lib/artillery.pyc
yac/lib/boot.py
yac/lib/boot.pyc
yac/lib/cache.py
yac/lib/cache.pyc
yac/lib/db.py
yac/lib/file.py
yac/lib/file.pyc
yac/lib/file_converter.py
yac/lib/file_converter.pyc
yac/lib/inputs.py
yac/lib/inputs.pyc
yac/lib/intrinsic.py
yac/lib/intrinsic.pyc
yac/lib/keepass.py
yac/lib/keepass.pyc
yac/lib/module.pyc
yac/lib/naming.py
yac/lib/naming.pyc
yac/lib/naming_default.py
yac/lib/params.py
yac/lib/params.pyc
yac/lib/paths.py
yac/lib/paths.pyc
yac/lib/registry.py
yac/lib/registry.pyc
yac/lib/secrets.py
yac/lib/secrets.pyc
yac/lib/service.py
yac/lib/service.pyc
yac/lib/stack.py
yac/lib/stack.pyc
yac/lib/state.py
yac/lib/state.pyc
yac/lib/task.py
yac/lib/task.pyc
yac/lib/template.py
yac/lib/template.pyc
yac/lib/test.pyc
yac/lib/validator.py
yac/lib/validator.pyc
yac/lib/variables.py
yac/lib/variables.pyc
yac/lib/version.py
yac/lib/version.pyc
yac/lib/vpc.py
yac/lib/vpc.pyc
yac/lib/container/__init__.py
yac/lib/container/__init__.pyc
yac/lib/container/api.py
