Metadata-Version: 1.1
Name: yac
Version: 1.4.6
Summary: yac - portable services
Home-page: https://bitbucket.org/thomas_b_jackson/yac
Author: Thomas Jackson
Author-email: thomas.b.jackson@gmail.com
License: MIT
Keywords: service cloudformation aws ecs docker
Platform: UNKNOWN
Classifier: Development Status :: 3 - Alpha
Classifier: License :: OSI Approved :: MIT License
Classifier: Programming Language :: Python :: 2.7
Classifier: Topic :: Text Processing :: Linguistic
